google/cloud/billing/budgets/__init__.py
google/cloud/billing/budgets/gapic_version.py
google/cloud/billing/budgets/py.typed
google/cloud/billing/budgets_v1/__init__.py
google/cloud/billing/budgets_v1/gapic_metadata.json
google/cloud/billing/budgets_v1/gapic_version.py
google/cloud/billing/budgets_v1/py.typed
google/cloud/billing/budgets_v1/services/__init__.py
google/cloud/billing/budgets_v1/services/budget_service/__init__.py
google/cloud/billing/budgets_v1/services/budget_service/async_client.py
google/cloud/billing/budgets_v1/services/budget_service/client.py
google/cloud/billing/budgets_v1/services/budget_service/pagers.py
google/cloud/billing/budgets_v1/services/budget_service/transports/__init__.py
google/cloud/billing/budgets_v1/services/budget_service/transports/base.py
google/cloud/billing/budgets_v1/services/budget_service/transports/grpc.py
google/cloud/billing/budgets_v1/services/budget_service/transports/grpc_asyncio.py
google/cloud/billing/budgets_v1/services/budget_service/transports/rest.py
google/cloud/billing/budgets_v1/services/budget_service/transports/rest_base.py
google/cloud/billing/budgets_v1/types/__init__.py
google/cloud/billing/budgets_v1/types/budget_model.py
google/cloud/billing/budgets_v1/types/budget_service.py
google/cloud/billing/budgets_v1beta1/__init__.py
google/cloud/billing/budgets_v1beta1/gapic_metadata.json
google/cloud/billing/budgets_v1beta1/gapic_version.py
google/cloud/billing/budgets_v1beta1/py.typed
google/cloud/billing/budgets_v1beta1/services/__init__.py
google/cloud/billing/budgets_v1beta1/services/budget_service/__init__.py
google/cloud/billing/budgets_v1beta1/services/budget_service/async_client.py
google/cloud/billing/budgets_v1beta1/services/budget_service/client.py
google/cloud/billing/budgets_v1beta1/services/budget_service/pagers.py
google/cloud/billing/budgets_v1beta1/services/budget_service/transports/__init__.py
google/cloud/billing/budgets_v1beta1/services/budget_service/transports/base.py
google_cloud_billing_budgets-1.19.0.dist-info/licenses/LICENSE
google_cloud_billing_budgets-1.19.0.dist-info/METADATA
google_cloud_billing_budgets-1.19.0.dist-info/WHEEL
google_cloud_billing_budgets-1.19.0.dist-info/top_level.txt
google_cloud_billing_budgets-1.19.0.dist-info/RECORD
